LICENSE
README.md
setup.cfg
setup.py
pyzorder/__init__.py
pyzorder/pymorton.py
pyzorder/pyzorder.py
pyzorder.egg-info/PKG-INFO
pyzorder.egg-info/SOURCES.txt
pyzorder.egg-info/dependency_links.txt
pyzorder.egg-info/top_level.txt