Metadata-Version: 2.1
Name: pyzorder
Version: 0.0.2
Summary: z-order curve (a.k.a. Morton order) implementation in Python
Home-page: https://github.com/smatsumoto78/pyzorder
Author: Shinji Matsumoto
Author-email: s.kawagt@gmail.com
License: MIT
Platform: UNKNOWN
License-File: LICENSE
